LICENSE
MANIFEST.in
README.md
requirements-dev.txt
requirements.txt
setup.cfg
setup.py
cli/__init__.py
cli/constants.py
cli/entrypoint.py
cli/utils.py
cli/generate/__init__.py
cli/generate/cli.py
cli/generate/forms.py
cli/generate/help.py
eos_name_generator/__init__.py
eos_name_generator/constants.py
eos_name_generator/errors.py
eos_name_generator/interfaces.py
eos_name_generator.egg-info/PKG-INFO
eos_name_generator.egg-info/SOURCES.txt
eos_name_generator.egg-info/dependency_links.txt
eos_name_generator.egg-info/entry_points.txt
eos_name_generator.egg-info/requires.txt
eos_name_generator.egg-info/top_level.txt
eos_name_generator/markov_chain_generator/__init__.py
eos_name_generator/markov_chain_generator/generator.py
eos_name_generator/random_generator/__init__.py
eos_name_generator/random_generator/data_reader.py
eos_name_generator/random_generator/generator.py
eos_name_generator/random_generator/seed_data/nounlist.txt
eos_name_generator/rnn_generator/__init__.py
eos_name_generator/rnn_generator/generator.py
eos_name_generator/utils/__init__.py
eos_name_generator/utils/fast_random_choice/__init__.py
eos_name_generator/utils/fast_random_choice/fast_random_choice.py
eos_name_generator/utils/fast_random_choice/interfaces.py