Metadata-Version: 2.1
Name: eos-name-generator
Version: 0.2.0
Summary: Python package for generation random name which suits `EOS` name conversations
Home-page: https://github.com/Alladin9393/name-generator
Author: Alladin9393
Author-email: ember.toon@protonmail.com
License: MIT
Platform: UNKNOWN
Classifier: Operating System :: OS Independent
Classifier: Intended Audience :: Developers
Classifier: License :: OSI Approved :: MIT License
Classifier: Programming Language :: Python :: 3.4
Classifier: Programming Language :: Python :: 3.5
Classifier: Programming Language :: Python :: 3.6
Classifier: Programming Language :: Python :: 3.7
